azure/monitor/__init__.py
azure/monitor/monitor_client.py
azure/monitor/version.py
azure/monitor/models/__init__.py
azure/monitor/models/error_response.py
azure/monitor/models/event_data.py
azure/monitor/models/event_data_paged.py
azure/monitor/models/http_request_info.py
azure/monitor/models/localizable_string.py
azure/monitor/models/localizable_string_paged.py
azure/monitor/models/metric.py
azure/monitor/models/metric_availability.py
azure/monitor/models/metric_definition.py
azure/monitor/models/metric_definition_paged.py
azure/monitor/models/metric_paged.py
azure/monitor/models/metric_value.py
azure/monitor/models/monitor_client_enums.py
azure/monitor/models/sender_authorization.py
azure/monitor/models/usage_metric.py
azure/monitor/models/usage_metric_paged.py
azure/monitor/operations/__init__.py
azure/monitor/operations/activity_logs_operations.py
azure/monitor/operations/event_categories_operations.py
azure/monitor/operations/metric_definitions_operations.py
azure/monitor/operations/metrics_operations.py
azure/monitor/operations/tenant_activity_logs_operations.py
azure/monitor/operations/usage_metrics_operations.py
azure_monitor-0.3.1.dist-info/DESCRIPTION.rst
azure_monitor-0.3.1.dist-info/METADATA
azure_monitor-0.3.1.dist-info/RECORD
azure_monitor-0.3.1.dist-info/WHEEL
azure_monitor-0.3.1.dist-info/metadata.json
azure_monitor-0.3.1.dist-info/top_level.txt
